{
  "id": "a699a8f0dc19f52820e7b314bc76b345f810ffbb",
  "url": "https://www.ech.nl/stichting-ech-feliciteert-de-knb-met-haar-175e-jubileum/",
  "title": "Stichting ECH feliciteert de KNB met haar 175e jubileum! - ECH",
  "text": "Stichting ECH feliciteert de KNB met haar 175e jubileum! - ECH Ga naar de inhoud ECH Nieuws Vacatures Inschrijven nieuwsbrief Veelgestelde vragen Inloggen Voor notarissen Voor hypothecair financiers Zo werkt ECH Over ons Contact X Stichting ECH feliciteert de KNB met haar 175e jubileum! / Nieuws / Door Ruby Het notariaat is dan wellicht een ‘oud’ ambt, het beleid van de KNB is modern en vooruitstrevend. Er is ontzettend veel veranderd in 175 jaar. Nog dagelijks biedt de notaris rECHtszekerheid en vertrouwen, waardoor we ‘s nachts beter slapen. Hulde aan het verleden én de toekomst! We zijn blij met het vertrouwen dat de KNB aan ECH geeft en zijn er trots op dat we een steentje mogen bijdragen aan de digitalisering en versteviging van dit mooie beroep zonder afbreuk te doen aan de kernwaarden. Wij wensen alle (kandidaat-)notarissen van nederland en KNB-medewerkers een geweldige dag toe! Deel dit bericht! Bericht navigatie ← Vorige Bericht Volgende Bericht → Op de hoogte blijven? Meld je aan voor de nieuwsbrief. Stichting ECH Spui 184 2511 BW Den Haag info@ech.nl 070 – 3307111 KVK-nummer 27259827 BTW-nummer 812411778B01 Voor notarissen Voor hypothecair financiers Zo werkt ECH Over ons Vacatures Contact Nieuws Veelgestelde vragen Inloggen Onderhoud & storingen © Elektronische Communicatie Hypotheken (2020). Lees hier ons Privacy Statement .",
  "retrieved_at": "2025-05-19T04:08:30Z",
  "source": "ech.nl"
}